README.txt
setup.py
teleterm/__init__.py
teleterm/tele.py
teleterm.egg-info/PKG-INFO
teleterm.egg-info/SOURCES.txt
teleterm.egg-info/dependency_links.txt
teleterm.egg-info/entry_points.txt
teleterm.egg-info/requires.txt
teleterm.egg-info/top_level.txt