Metadata-Version: 2.1
Name: teleterm
Version: 0.0.9
Summary: teleterm
Home-page: https://duckduckgo.com
Author: Ragar Rysuv
License: UNKNOWN
Platform: UNKNOWN
Classifier: Development Status :: 1 - Planning
Classifier: Programming Language :: Python :: 3.7
Classifier: Operating System :: POSIX :: Linux
